ctstruct/__init__.py
ctstruct-0.1.0b0.dist-info/WHEEL
ctstruct-0.1.0b0.dist-info/METADATA
ctstruct-0.1.0b0.dist-info/RECORD
