Metadata-Version: 2.4
Name: ctstruct
Version: 0.1.0b0
Summary: Creating ctype structure like dataclass
Author: ZhengYu, Xu
Author-email: ZhengYu, Xu <zen-xu@outlook.com>
License-Expression: MIT
Classifier: License :: OSI Approved :: MIT License
Classifier: Programming Language :: Python
Classifier: Programming Language :: Python :: 3
Classifier: Programming Language :: Python :: 3 :: Only
Classifier: Programming Language :: Python :: 3.9
Classifier: Programming Language :: Python :: 3.10
Classifier: Programming Language :: Python :: 3.11
Classifier: Programming Language :: Python :: 3.12
Classifier: Programming Language :: Python :: 3.13
Requires-Dist: typing-extensions ; python_full_version < '3.11'
Requires-Python: >=3.9
Project-URL: homepage, https://github.com/zen-xu/ctstruct
Project-URL: issues, https://github.com/zen-xu/ctstruct/issues
Project-URL: repository, https://github.com/zen-xu/ctstruct.git
